only_common/__init__.py
only_common/only_common.py
only_common-2.1.0.dist-info/METADATA
only_common-2.1.0.dist-info/WHEEL
only_common-2.1.0.dist-info/top_level.txt
only_common-2.1.0.dist-info/RECORD
